{
	"archive" : {},
	"artifacts" : 
	[
		{
			"path" : "desktop_devx/out/provisioning_client/libhsm_security_client.a"
		}
	],
	"backtrace" : 1,
	"backtraceGraph" : 
	{
		"commands" : 
		[
			"add_library",
			"install",
			"target_link_libraries",
			"linkSharedUtil",
			"add_compile_definitions",
			"include",
			"add_definitions",
			"include_directories"
		],
		"files" : 
		[
			"DesktopDevX/azure-iot-sdk-c/provisioning_client/CMakeLists.txt",
			"DesktopDevX/azure-iot-sdk-c/configs/azure_iot_sdksFunctions.cmake",
			"CMakeLists.txt",
			"cmake/altair_config.cmake",
			"DesktopDevX/azure-iot-sdk-c/CMakeLists.txt",
			"DesktopDevX/azure-iot-sdk-c/dependencies.cmake"
		],
		"nodes" : 
		[
			{
				"file" : 0
			},
			{
				"command" : 0,
				"file" : 0,
				"line" : 182,
				"parent" : 0
			},
			{
				"command" : 1,
				"file" : 0,
				"line" : 402,
				"parent" : 0
			},
			{
				"command" : 3,
				"file" : 0,
				"line" : 184,
				"parent" : 0
			},
			{
				"command" : 2,
				"file" : 1,
				"line" : 103,
				"parent" : 3
			},
			{
				"command" : 2,
				"file" : 0,
				"line" : 185,
				"parent" : 0
			},
			{
				"file" : 2
			},
			{
				"command" : 4,
				"file" : 2,
				"line" : 84,
				"parent" : 6
			},
			{
				"command" : 5,
				"file" : 2,
				"line" : 7,
				"parent" : 6
			},
			{
				"file" : 3,
				"parent" : 8
			},
			{
				"command" : 4,
				"file" : 3,
				"line" : 19,
				"parent" : 9
			},
			{
				"command" : 4,
				"file" : 2,
				"line" : 12,
				"parent" : 6
			},
			{
				"command" : 4,
				"file" : 2,
				"line" : 34,
				"parent" : 6
			},
			{
				"file" : 4
			},
			{
				"command" : 6,
				"file" : 4,
				"line" : 180,
				"parent" : 13
			},
			{
				"command" : 4,
				"file" : 2,
				"line" : 32,
				"parent" : 6
			},
			{
				"command" : 4,
				"file" : 2,
				"line" : 41,
				"parent" : 6
			},
			{
				"command" : 4,
				"file" : 2,
				"line" : 40,
				"parent" : 6
			},
			{
				"command" : 6,
				"file" : 4,
				"line" : 28,
				"parent" : 13
			},
			{
				"command" : 4,
				"file" : 2,
				"line" : 13,
				"parent" : 6
			},
			{
				"command" : 4,
				"file" : 2,
				"line" : 15,
				"parent" : 6
			},
			{
				"command" : 4,
				"file" : 2,
				"line" : 14,
				"parent" : 6
			},
			{
				"command" : 4,
				"file" : 2,
				"line" : 31,
				"parent" : 6
			},
			{
				"command" : 4,
				"file" : 2,
				"line" : 17,
				"parent" : 6
			},
			{
				"command" : 4,
				"file" : 2,
				"line" : 33,
				"parent" : 6
			},
			{
				"command" : 4,
				"file" : 2,
				"line" : 18,
				"parent" : 6
			},
			{
				"command" : 4,
				"file" : 2,
				"line" : 49,
				"parent" : 6
			},
			{
				"command" : 4,
				"file" : 2,
				"line" : 25,
				"parent" : 6
			},
			{
				"command" : 4,
				"file" : 2,
				"line" : 24,
				"parent" : 6
			},
			{
				"command" : 4,
				"file" : 2,
				"line" : 27,
				"parent" : 6
			},
			{
				"command" : 4,
				"file" : 2,
				"line" : 35,
				"parent" : 6
			},
			{
				"command" : 4,
				"file" : 2,
				"line" : 28,
				"parent" : 6
			},
			{
				"command" : 7,
				"file" : 4,
				"line" : 292,
				"parent" : 13
			},
			{
				"command" : 7,
				"file" : 4,
				"line" : 293,
				"parent" : 13
			},
			{
				"command" : 5,
				"file" : 4,
				"line" : 295,
				"parent" : 13
			},
			{
				"file" : 5,
				"parent" : 34
			},
			{
				"command" : 7,
				"file" : 5,
				"line" : 42,
				"parent" : 35
			},
			{
				"command" : 7,
				"file" : 0,
				"line" : 84,
				"parent" : 0
			},
			{
				"command" : 7,
				"file" : 0,
				"line" : 85,
				"parent" : 0
			},
			{
				"command" : 7,
				"file" : 0,
				"line" : 86,
				"parent" : 0
			},
			{
				"command" : 7,
				"file" : 0,
				"line" : 106,
				"parent" : 0
			},
			{
				"command" : 7,
				"file" : 0,
				"line" : 164,
				"parent" : 0
			},
			{
				"command" : 7,
				"file" : 0,
				"line" : 167,
				"parent" : 0
			},
			{
				"command" : 7,
				"file" : 0,
				"line" : 171,
				"parent" : 0
			},
			{
				"command" : 7,
				"file" : 0,
				"line" : 304,
				"parent" : 0
			}
		]
	},
	"compileGroups" : 
	[
		{
			"compileCommandFragments" : 
			[
				{
					"fragment" : " -Werror -DUSE_PROV_MODULE_FULL -DUSE_PROV_MODULE -DUSE_PROV_MODULE -DHSM_TYPE_X509 -DHSM_TYPE_SAS_TOKEN -DHSM_TYPE_SYMM_KEY -g -arch arm64 -isysroot /Library/Developer/CommandLineTools/SDKs/MacOSX12.1.sdk"
				},
				{
					"fragment" : "-std=gnu99"
				}
			],
			"defines" : 
			[
				{
					"backtrace" : 7,
					"define" : "ALTAIR_FRONT_PANEL_NONE"
				},
				{
					"backtrace" : 10,
					"define" : "ALTAIR_MQTT_HOST=\"test.mosquitto.org\""
				},
				{
					"backtrace" : 11,
					"define" : "ALTAIR_MQTT_SECURE_PORT_WOLF=8884"
				},
				{
					"backtrace" : 12,
					"define" : "AZURE_SPHERE"
				},
				{
					"backtrace" : 14,
					"define" : "DONT_USE_UPLOADTOBLOB"
				},
				{
					"backtrace" : 15,
					"define" : "ENABLE_MQTT_TLS"
				},
				{
					"backtrace" : 16,
					"define" : "IOT_HUB_POLL_TIME_NANOSECONDS=500000000"
				},
				{
					"backtrace" : 17,
					"define" : "IOT_HUB_POLL_TIME_SECONDS=1"
				},
				{
					"backtrace" : 18,
					"define" : "MACOSX"
				},
				{
					"backtrace" : 19,
					"define" : "MQTT_CA_CERTIFICATE=\"certs/ca.crt\""
				},
				{
					"backtrace" : 20,
					"define" : "MQTT_CLIENT_CERTIFICATE=\"certs/client.crt\""
				},
				{
					"backtrace" : 21,
					"define" : "MQTT_CLIENT_PRIVATE_KEY=\"certs/client.key\""
				},
				{
					"backtrace" : 22,
					"define" : "MQTT_USE_WOLFSSL"
				},
				{
					"backtrace" : 23,
					"define" : "MQTT_WOLF_DRIVER"
				},
				{
					"backtrace" : 24,
					"define" : "NO_DH"
				},
				{
					"backtrace" : 25,
					"define" : "PRINTF=Log_Debug"
				},
				{
					"backtrace" : 5,
					"define" : "RIOTBUILD"
				},
				{
					"backtrace" : 5,
					"define" : "RIOTSECP256R1"
				},
				{
					"backtrace" : 26,
					"define" : "SD_CARD_ENABLED"
				},
				{
					"backtrace" : 27,
					"define" : "WOLFMQTT_DISCONNECT_CB"
				},
				{
					"backtrace" : 28,
					"define" : "WOLFMQTT_MULTITHREAD"
				},
				{
					"backtrace" : 29,
					"define" : "WOLFMQTT_NO_STDIO"
				},
				{
					"backtrace" : 30,
					"define" : "WOLFMQTT_USER_SETTINGS"
				},
				{
					"backtrace" : 31,
					"define" : "WOLFSSL_USER_SETTINGS"
				}
			],
			"includes" : 
			[
				{
					"backtrace" : 32,
					"path" : "/Users/dave/GitHub/AzureSphereAltair8800/AltairHL_emulator/DesktopDevX/azure-iot-sdk-c/deps/azure-macro-utils-c/inc"
				},
				{
					"backtrace" : 33,
					"path" : "/Users/dave/GitHub/AzureSphereAltair8800/AltairHL_emulator/DesktopDevX/azure-iot-sdk-c/deps/umock-c/inc"
				},
				{
					"backtrace" : 36,
					"path" : "/Users/dave/GitHub/AzureSphereAltair8800/AltairHL_emulator/DesktopDevX/azure-iot-sdk-c/c-utility/inc"
				},
				{
					"backtrace" : 36,
					"path" : "/Users/dave/GitHub/AzureSphereAltair8800/AltairHL_emulator/DesktopDevX/azure-iot-sdk-c/c-utility/pal/linux"
				},
				{
					"backtrace" : 37,
					"path" : "/Users/dave/GitHub/AzureSphereAltair8800/AltairHL_emulator/DesktopDevX/azure-iot-sdk-c/provisioning_client/./deps/RIoT/Simulation/DICE"
				},
				{
					"backtrace" : 38,
					"path" : "/Users/dave/GitHub/AzureSphereAltair8800/AltairHL_emulator/DesktopDevX/azure-iot-sdk-c/provisioning_client/./deps/RIoT/Simulation/RIoT/Core"
				},
				{
					"backtrace" : 39,
					"path" : "/Users/dave/GitHub/AzureSphereAltair8800/AltairHL_emulator/DesktopDevX/azure-iot-sdk-c/provisioning_client/./deps/RIoT/Simulation/RIoT/Core/RIoTCrypt/include"
				},
				{
					"backtrace" : 40,
					"path" : "/Users/dave/GitHub/AzureSphereAltair8800/AltairHL_emulator/DesktopDevX/azure-iot-sdk-c/provisioning_client/deps/utpm/inc"
				},
				{
					"backtrace" : 41,
					"path" : "/Users/dave/GitHub/AzureSphereAltair8800/AltairHL_emulator/DesktopDevX/azure-iot-sdk-c/provisioning_client/inc"
				},
				{
					"backtrace" : 41,
					"path" : "/Users/dave/GitHub/AzureSphereAltair8800/AltairHL_emulator/DesktopDevX/azure-iot-sdk-c/provisioning_client/inc/internal"
				},
				{
					"backtrace" : 42,
					"path" : "/Users/dave/GitHub/AzureSphereAltair8800/AltairHL_emulator/DesktopDevX/azure-iot-sdk-c/provisioning_client/../deps/parson"
				},
				{
					"backtrace" : 43,
					"path" : "/Users/dave/GitHub/AzureSphereAltair8800/AltairHL_emulator/DesktopDevX/azure-iot-sdk-c/provisioning_client/adapters"
				},
				{
					"backtrace" : 44,
					"path" : "/Users/dave/GitHub/AzureSphereAltair8800/AltairHL_emulator/DesktopDevX/azure-iot-sdk-c/umqtt/inc"
				},
				{
					"backtrace" : 5,
					"path" : "/Users/dave/GitHub/AzureSphereAltair8800/AltairHL_emulator/DesktopDevX/azure-iot-sdk-c/provisioning_client/deps/RIoT/Simulation/DICE"
				},
				{
					"backtrace" : 5,
					"path" : "/Users/dave/GitHub/AzureSphereAltair8800/AltairHL_emulator/DesktopDevX/azure-iot-sdk-c/provisioning_client/deps/RIoT/Simulation/RIoT/Core"
				},
				{
					"backtrace" : 5,
					"path" : "/Users/dave/GitHub/AzureSphereAltair8800/AltairHL_emulator/DesktopDevX/azure-iot-sdk-c/provisioning_client/deps/RIoT/Simulation/RIoT/Core/RIoTCrypt/include"
				},
				{
					"backtrace" : 5,
					"path" : "/Users/dave/GitHub/AzureSphereAltair8800/AltairHL_emulator/DesktopDevX/azure-iot-sdk-c/provisioning_client/deps/RIoT/Simulation/RIoT/Core/RIoTCrypt/include/mbedtls"
				}
			],
			"language" : "C",
			"languageStandard" : 
			{
				"backtraces" : 
				[
					1
				],
				"standard" : "99"
			},
			"sourceIndexes" : 
			[
				0,
				1,
				2,
				3
			]
		}
	],
	"dependencies" : 
	[
		{
			"backtrace" : 4,
			"id" : "aziotsharedutil::@d20dc724c4939fdee891"
		},
		{
			"backtrace" : 5,
			"id" : "msr_riot::@8437e2f640d24f60da41"
		},
		{
			"backtrace" : 5,
			"id" : "utpm::@48e1eddd51e2694db2c6"
		}
	],
	"id" : "hsm_security_client::@cd2c1869d613d402d732",
	"install" : 
	{
		"destinations" : 
		[
			{
				"backtrace" : 2,
				"path" : "lib"
			}
		],
		"prefix" : 
		{
			"path" : "/usr/local"
		}
	},
	"name" : "hsm_security_client",
	"nameOnDisk" : "libhsm_security_client.a",
	"paths" : 
	{
		"build" : "desktop_devx/out/provisioning_client",
		"source" : "DesktopDevX/azure-iot-sdk-c/provisioning_client"
	},
	"sourceGroups" : 
	[
		{
			"name" : "Source Files",
			"sourceIndexes" : 
			[
				0,
				1,
				2,
				3
			]
		},
		{
			"name" : "Header Files",
			"sourceIndexes" : 
			[
				4,
				5,
				6,
				7
			]
		}
	],
	"sources" : 
	[
		{
			"backtrace" : 1,
			"compileGroupIndex" : 0,
			"path" : "DesktopDevX/azure-iot-sdk-c/provisioning_client/adapters/hsm_client_data.c",
			"sourceGroupIndex" : 0
		},
		{
			"backtrace" : 1,
			"compileGroupIndex" : 0,
			"path" : "DesktopDevX/azure-iot-sdk-c/provisioning_client/adapters/hsm_client_riot.c",
			"sourceGroupIndex" : 0
		},
		{
			"backtrace" : 1,
			"compileGroupIndex" : 0,
			"path" : "DesktopDevX/azure-iot-sdk-c/provisioning_client/adapters/hsm_client_tpm.c",
			"sourceGroupIndex" : 0
		},
		{
			"backtrace" : 1,
			"compileGroupIndex" : 0,
			"path" : "DesktopDevX/azure-iot-sdk-c/provisioning_client/adapters/hsm_client_key.c",
			"sourceGroupIndex" : 0
		},
		{
			"backtrace" : 1,
			"path" : "DesktopDevX/azure-iot-sdk-c/provisioning_client/adapters/hsm_client_data.h",
			"sourceGroupIndex" : 1
		},
		{
			"backtrace" : 1,
			"path" : "DesktopDevX/azure-iot-sdk-c/provisioning_client/adapters/hsm_client_riot.h",
			"sourceGroupIndex" : 1
		},
		{
			"backtrace" : 1,
			"path" : "DesktopDevX/azure-iot-sdk-c/provisioning_client/adapters/hsm_client_tpm.h",
			"sourceGroupIndex" : 1
		},
		{
			"backtrace" : 1,
			"path" : "DesktopDevX/azure-iot-sdk-c/provisioning_client/adapters/hsm_client_key.h",
			"sourceGroupIndex" : 1
		}
	],
	"type" : "STATIC_LIBRARY"
}
